class MainActivity: AppCompatActivity() {

    lateinit var tvTest: TextView

    override fun onCreate(savedInstanceState: Bundle?) {
        super.onCreate(savedInstanceState)
        setContentView(R.layout.activity_main)
        tvTest = findViewById(R.id.tvTest)
        val hello = LiLei.hello()
        val hello2 = LiLeiKt.hello()
        tvTest.text = hello
    }
}


val hello = LiLei.hello() //调用java static会生成一条指令
30: invokestatic  #62                 // Method com/example/testgradlepluginasm/LiLei.hello:()Ljava/lang/String;

val hello2 = LiLeiKt.hello() //调用kotlin companion方法会生成两条指令
34: getstatic     #68                 // Field com/example/testgradlepluginasm/LiLeiKt.Companion:Lcom/example/testgradlepluginasm/LiLeiKt$Companion;
37: invokevirtual #71                 // Method com/example/testgradlepluginasm/LiLeiKt$Companion.hello:()Ljava/lang/String;


➜  debug pwd
...TestGradlePluginAsm/app/build/tmp/kotlin-classes/debug
➜  debug javap -c com.example.testgradlepluginasm.MainActivity
Compiled from "MainActivity.kt"
public final class com.example.testgradlepluginasm.MainActivity extends androidx.appcompat.app.AppCompatActivity {
  public android.widget.TextView tvTest;

  public com.example.testgradlepluginasm.MainActivity();
    Code:
       0: aload_0
       1: invokespecial #8                  // Method androidx/appcompat/app/AppCompatActivity."<init>":()V
       4: return

  public final android.widget.TextView getTvTest();
    Code:
       0: aload_0
       1: getfield      #17                 // Field tvTest:Landroid/widget/TextView;
       4: dup
       5: ifnull        9
       8: areturn
       9: pop
      10: ldc           #18                 // String tvTest
      12: invokestatic  #24                 // Method kotlin/jvm/internal/Intrinsics.throwUninitializedPropertyAccessException:(Ljava/lang/String;)V
      15: aconst_null
      16: areturn

  public final void setTvTest(android.widget.TextView);
    Code:
       0: aload_1
       1: ldc           #30                 // String <set-?>
       3: invokestatic  #34                 // Method kotlin/jvm/internal/Intrinsics.checkNotNullParameter:(Ljava/lang/Object;Ljava/lang/String;)V
       6: aload_0
       7: aload_1
       8: putfield      #17                 // Field tvTest:Landroid/widget/TextView;
      11: return

  protected void onCreate(android.os.Bundle);
    Code:
       0: aload_0
       1: aload_1
       2: invokespecial #39                 // Method androidx/appcompat/app/AppCompatActivity.onCreate:(Landroid/os/Bundle;)V
       5: aload_0
       6: ldc           #40                 // int 2131427356
       8: invokevirtual #44                 // Method setContentView:(I)V
      11: aload_0
      12: aload_0
      13: ldc           #45                 // int 2131231124
      15: invokevirtual #49                 // Method findViewById:(I)Landroid/view/View;
      18: dup
      19: ldc           #51                 // String findViewById(R.id.tvTest)
      21: invokestatic  #54                 // Method kotlin/jvm/internal/Intrinsics.checkNotNullExpressionValue:(Ljava/lang/Object;Ljava/lang/String;)V
      24: checkcast     #26                 // class android/widget/TextView
      27: invokevirtual #56                 // Method setTvTest:(Landroid/widget/TextView;)V
      30: invokestatic  #62                 // Method com/example/testgradlepluginasm/LiLei.hello:()Ljava/lang/String;
      33: astore_2
      34: getstatic     #68                 // Field com/example/testgradlepluginasm/LiLeiKt.Companion:Lcom/example/testgradlepluginasm/LiLeiKt$Companion;
      37: invokevirtual #71                 // Method com/example/testgradlepluginasm/LiLeiKt$Companion.hello:()Ljava/lang/String;
      40: astore_3
      41: aload_0
      42: invokevirtual #73                 // Method getTvTest:()Landroid/widget/TextView;
      45: aload_2
      46: checkcast     #75                 // class java/lang/CharSequence
      49: invokevirtual #79                 // Method android/widget/TextView.setText:(Ljava/lang/CharSequence;)V
      52: return
}


